qvapay/__init__.py
qvapay/v1/__init__.py
qvapay/v1/_async/__init__.py
qvapay/v1/_async/client.py
qvapay/v1/_sync/__init__.py
qvapay/v1/_sync/client.py
qvapay/v1/auth.py
qvapay/v1/errors.py
qvapay/v1/http_clients.py
qvapay/v1/models/__init__.py
qvapay/v1/models/info.py
qvapay/v1/models/invoice.py
qvapay/v1/models/link.py
qvapay/v1/models/owner.py
qvapay/v1/models/paginated_transactions.py
qvapay/v1/models/paid_by.py
qvapay/v1/models/transaction.py
qvapay/v1/models/transaction_detail.py
qvapay/v1/utils.py
qvapay-0.3.0.dist-info/LICENSE
qvapay-0.3.0.dist-info/WHEEL
qvapay-0.3.0.dist-info/METADATA
qvapay-0.3.0.dist-info/RECORD
