Metadata-Version: 2.1
Name: qvapay
Version: 0.3.0
Summary: Python SDK for the QvaPay API
Home-page: https://github.com/lugodev/qvapay-python
License: MIT
Keywords: QvaPay,api,payments
Author: Carlos Lugones
Author-email: contact@lugodev.com
Requires-Python: >=3.8,<4.0
Classifier: Development Status :: 4 - Beta
Classifier: Intended Audience :: Developers
Classifier: License :: OSI Approved :: MIT License
Classifier: Programming Language :: Python :: 2
Classifier: Programming Language :: Python :: 3
Classifier: Programming Language :: Python :: 3.10
Classifier: Programming Language :: Python :: 3.8
Classifier: Programming Language :: Python :: 3.9
Requires-Dist: httpx (>=0.20.0,<0.21.0)
Requires-Dist: python-dateutil (>=2.8.2,<3.0.0)
Requires-Dist: python-dotenv (>=0.19.1,<0.20.0)
Project-URL: Documentation, https://github.com/lugodev/qvapay-python
Project-URL: Repository, https://github.com/lugodev/qvapay-python
Project-URL: Tracker, https://github.com/lugodev/qvapay-python/issues
